picoFFT/__init__.py
picoFFT/fft.py
picoFFT/train.py
picoFFT/input/__init__.py
picoFFT/input/tokenizer.py
picoFFT-0.1.dist-info/METADATA
picoFFT-0.1.dist-info/WHEEL
picoFFT-0.1.dist-info/top_level.txt
picoFFT-0.1.dist-info/RECORD
