Metadata-Version: 2.1
Name: picoFFT
Version: 0.1
Summary: picoFFT: impossible is possible LLM
Author: Timur Ishuov
